iflow_mcp_mcp_smart_customer_support-0.1.0.dist-info/licenses/LICENSE
mcp_smart_customer_support/__init__.py
mcp_smart_customer_support/human_customer_service.py
mcp_smart_customer_support/mcp_server.py
mcp_smart_customer_support/order_operations.py
mcp_smart_customer_support/product_knowledge.py
iflow_mcp_mcp_smart_customer_support-0.1.0.dist-info/METADATA
iflow_mcp_mcp_smart_customer_support-0.1.0.dist-info/WHEEL
iflow_mcp_mcp_smart_customer_support-0.1.0.dist-info/entry_points.txt
iflow_mcp_mcp_smart_customer_support-0.1.0.dist-info/top_level.txt
iflow_mcp_mcp_smart_customer_support-0.1.0.dist-info/RECORD
