Metadata-Version: 2.4
Name: iflow-mcp_mcp-smart-customer-support
Version: 0.1.0
Summary: 智能客服示例
Author-email: ggguo <ggguo@example.com>
Requires-Python: >=3.10
License-File: LICENSE
Requires-Dist: mcp[cli]>=1.6.0
Requires-Dist: python-dotenv
Dynamic: license-file
